AioBroker/__init__.py
AioBroker/__main__.py
AioBroker/broker.py
AioBroker/decorators.py
AioBrokerTools/__init__.py
AioBrokerTools/__main__.py
AioBrokerTools/broker.py
AioBrokerTools/decorators.py
AioBrokerTools-0.1.0.dist-info/METADATA
AioBrokerTools-0.1.0.dist-info/WHEEL
AioBrokerTools-0.1.0.dist-info/top_level.txt
AioBrokerTools-0.1.0.dist-info/RECORD
